nonebot_plugin_bili2mp4/__init__.py
nonebot_plugin_bili2mp4/config.py
nonebot_plugin_bili2mp4/main.py
nonebot_plugin_bili2mp4-0.1.9.dist-info/METADATA
nonebot_plugin_bili2mp4-0.1.9.dist-info/WHEEL
nonebot_plugin_bili2mp4-0.1.9.dist-info/top_level.txt
nonebot_plugin_bili2mp4-0.1.9.dist-info/RECORD
