Metadata-Version: 2.4
Name: nonebot-plugin-bili2mp4
Version: 0.1.9
Summary: 在指定群内将B站小程序/分享链接解析转MP4后发送的NoneBot2插件
Author-email: j1udu <2312410042@stu.suda.edu.cn>
Project-URL: Homepage, https://github.com/j1udu/nonebot-plugin-bili2mp4
Project-URL: Repository, https://github.com/j1udu/nonebot-plugin-bili2mp4
Project-URL: Bug Reports, https://github.com/j1udu/nonebot-plugin-bili2mp4/issues
Keywords: nonebot,nonebot2,bilibili,video,download,mp4
Classifier: Programming Language :: Python :: 3
Classifier: Programming Language :: Python :: 3.8
Classifier: Programming Language :: Python :: 3.9
Classifier: Programming Language :: Python :: 3.10
Classifier: Programming Language :: Python :: 3.11
Classifier: License :: OSI Approved :: MIT License
Classifier: Operating System :: OS Independent
Requires-Python: <4.0,>=3.8
Requires-Dist: nonebot2>=2.3.0
Requires-Dist: nonebot-adapter-onebot>=2.0.0
Requires-Dist: nonebot-plugin-localstore<1.0.0,>=0.7.4
Requires-Dist: pydantic>=1.10.0
Requires-Dist: yt-dlp>=2023.3.4
Requires-Dist: aiofiles>=0.8.0
Provides-Extra: test
Requires-Dist: pytest>=7.0.0; extra == "test"
Requires-Dist: pytest-asyncio>=0.21.0; extra == "test"
Provides-Extra: dev
Requires-Dist: black>=22.0.0; extra == "dev"
Requires-Dist: isort>=5.10.0; extra == "dev"
Requires-Dist: flake8>=4.0.0; extra == "dev"
Requires-Dist: pytest>=7.0.0; extra == "dev"
Requires-Dist: pytest-asyncio>=0.21.0; extra == "dev"
Requires-Dist: pre-commit>=2.20.0; extra == "dev"
